{
    "callbacks": [],
    "functionName": "_image_get_preview_ratio",
    "filename": "wp-admin/includes/image-edit.php",
    "docCommentLine": 395,
    "startLine": 405,
    "endLine": 408,
    "calls": {
        "wp-admin/includes/image-edit.php:606": [
            "wp-admin/includes/image-edit.php",
            606
        ],
        "wp-admin/includes/image-edit.php:609": [
            "wp-admin/includes/image-edit.php",
            609
        ],
        "wp-admin/includes/image-edit.php:650": [
            "wp-admin/includes/image-edit.php",
            650
        ]
    },
    ":class": "ShrinkPress\\Build\\Entity\\Funcs\\WordPress_Func"
}