{
    "callbacks": [],
    "functionName": "_wp_post_thumbnail_html",
    "filename": "wp-admin/includes/post.php",
    "docCommentLine": 1492,
    "startLine": 1501,
    "endLine": 1566,
    "calls": {
        "wp-admin/includes/ajax-actions.php:2644": [
            "wp-admin/includes/ajax-actions.php",
            2644
        ],
        "wp-admin/includes/ajax-actions.php:2652": [
            "wp-admin/includes/ajax-actions.php",
            2652
        ],
        "wp-admin/includes/ajax-actions.php:2680": [
            "wp-admin/includes/ajax-actions.php",
            2680
        ],
        "wp-admin/includes/meta-boxes.php:1373": [
            "wp-admin/includes/meta-boxes.php",
            1373
        ]
    },
    ":class": "ShrinkPress\\Build\\Entity\\Funcs\\WordPress_Func"
}