{
    "callbacks": [],
    "functionName": "bloginfo",
    "filename": "wp-includes/general-template.php",
    "docCommentLine": 644,
    "startLine": 653,
    "endLine": 655,
    "calls": {
        "wp-admin/includes/class-custom-image-header.php:539": [
            "wp-admin/includes/class-custom-image-header.php",
            539
        ],
        "wp-admin/includes/class-custom-image-header.php:540": [
            "wp-admin/includes/class-custom-image-header.php",
            540
        ],
        "wp-admin/includes/media.php:518": [
            "wp-admin/includes/media.php",
            518
        ],
        "wp-admin/includes/template.php:1965": [
            "wp-admin/includes/template.php",
            1965
        ],
        "wp-admin/includes/template.php:2452": [
            "wp-admin/includes/template.php",
            2452
        ],
        "wp-admin/upgrade.php:62": [
            "wp-admin/upgrade.php",
            62
        ],
        "wp-includes/customize/class-wp-customize-site-icon-control.php:71": [
            "wp-includes/customize/class-wp-customize-site-icon-control.php",
            71
        ],
        "wp-includes/feed-atom.php:36": [
            "wp-includes/feed-atom.php",
            36
        ],
        "wp-includes/media-template.php:1449": [
            "wp-includes/media-template.php",
            1449
        ],
        "wp-includes/theme-compat/header.php:22": [
            "wp-includes/theme-compat/header.php",
            22
        ],
        "wp-includes/theme-compat/header.php:26": [
            "wp-includes/theme-compat/header.php",
            26
        ],
        "wp-includes/theme-compat/header.php:27": [
            "wp-includes/theme-compat/header.php",
            27
        ],
        "wp-includes/theme-compat/header.php:36": [
            "wp-includes/theme-compat/header.php",
            36
        ],
        "wp-includes/theme-compat/header.php:38": [
            "wp-includes/theme-compat/header.php",
            38
        ],
        "wp-includes/theme-compat/header.php:56": [
            "wp-includes/theme-compat/header.php",
            56
        ],
        "wp-includes/theme-compat/header.php:57": [
            "wp-includes/theme-compat/header.php",
            57
        ],
        "wp-login.php:96": [
            "wp-login.php",
            96
        ]
    },
    ":class": "ShrinkPress\\Index\\Entity\\Funcs\\WordPress_Func"
}