{
    "callbacks": [],
    "functionName": "get_user_meta",
    "filename": "wp-includes/user.php",
    "docCommentLine": 816,
    "startLine": 827,
    "endLine": 829,
    "calls": {
        "wp-admin/edit-form-blocks.php:313": [
            "wp-admin/edit-form-blocks.php",
            313
        ],
        "wp-admin/includes/ajax-actions.php:2853": [
            "wp-admin/includes/ajax-actions.php",
            2853
        ],
        "wp-admin/includes/ajax-actions.php:3461": [
            "wp-admin/includes/ajax-actions.php",
            3461
        ],
        "wp-admin/includes/class-wp-internal-pointers.php:79": [
            "wp-admin/includes/class-wp-internal-pointers.php",
            79
        ],
        "wp-admin/includes/class-wp-screen.php:1123": [
            "wp-admin/includes/class-wp-screen.php",
            1123
        ],
        "wp-admin/includes/meta-boxes.php:1510": [
            "wp-admin/includes/meta-boxes.php",
            1510
        ],
        "wp-admin/includes/ms.php:767": [
            "wp-admin/includes/ms.php",
            767
        ],
        "wp-admin/includes/post.php:2350": [
            "wp-admin/includes/post.php",
            2350
        ],
        "wp-admin/includes/upgrade.php:1155": [
            "wp-admin/includes/upgrade.php",
            1155
        ],
        "wp-admin/includes/upgrade.php:1157": [
            "wp-admin/includes/upgrade.php",
            1157
        ],
        "wp-admin/index.php:121": [
            "wp-admin/index.php",
            121
        ],
        "wp-admin/plugin-editor.php:307": [
            "wp-admin/plugin-editor.php",
            307
        ],
        "wp-admin/post.php:339": [
            "wp-admin/post.php",
            339
        ],
        "wp-admin/theme-editor.php:340": [
            "wp-admin/theme-editor.php",
            340
        ],
        "wp-admin/user-edit.php:98": [
            "wp-admin/user-edit.php",
            98
        ],
        "wp-admin/user-edit.php:513": [
            "wp-admin/user-edit.php",
            513
        ],
        "wp-includes/class-wp-user-meta-session-tokens.php:27": [
            "wp-includes/class-wp-user-meta-session-tokens.php",
            27
        ],
        "wp-includes/class-wp-user.php:318": [
            "wp-includes/class-wp-user.php",
            318
        ],
        "wp-includes/class-wp-user.php:871": [
            "wp-includes/class-wp-user.php",
            871
        ],
        "wp-includes/ms-functions.php:55": [
            "wp-includes/ms-functions.php",
            55
        ],
        "wp-includes/ms-functions.php:85": [
            "wp-includes/ms-functions.php",
            85
        ],
        "wp-includes/ms-functions.php:88": [
            "wp-includes/ms-functions.php",
            88
        ],
        "wp-includes/ms-functions.php:197": [
            "wp-includes/ms-functions.php",
            197
        ],
        "wp-includes/ms-functions.php:262": [
            "wp-includes/ms-functions.php",
            262
        ],
        "wp-includes/ms-site.php:772": [
            "wp-includes/ms-site.php",
            772
        ],
        "wp-includes/user.php:627": [
            "wp-includes/user.php",
            627
        ],
        "wp-includes/user.php:762": [
            "wp-includes/user.php",
            762
        ],
        "wp-includes/user.php:1951": [
            "wp-includes/user.php",
            1951
        ],
        "wp-includes/user.php:2902": [
            "wp-includes/user.php",
            2902
        ],
        "wp-includes/user.php:2966": [
            "wp-includes/user.php",
            2966
        ],
        "wp-includes/widgets/class-wp-widget-text.php:519": [
            "wp-includes/widgets/class-wp-widget-text.php",
            519
        ]
    },
    ":class": "ShrinkPress\\Reframe\\Entity\\Funcs\\WordPress_Func"
}