{
    "callbacks": [],
    "functionName": "hash_hmac",
    "filename": "wp-includes/compat.php",
    "docCommentLine": 221,
    "startLine": 244,
    "endLine": 246,
    "calls": {
        "wp-includes/class-smtp.php:501": [
            "wp-includes/class-smtp.php",
            501
        ],
        "wp-includes/class-wp-recovery-mode-cookie-service.php:231": [
            "wp-includes/class-wp-recovery-mode-cookie-service.php",
            231
        ],
        "wp-includes/pluggable.php:667": [
            "wp-includes/pluggable.php",
            667
        ],
        "wp-includes/pluggable.php:744": [
            "wp-includes/pluggable.php",
            744
        ],
        "wp-includes/pluggable.php:2295": [
            "wp-includes/pluggable.php",
            2295
        ],
        "wp-includes/pluggable.php:2318": [
            "wp-includes/pluggable.php",
            2318
        ],
        "wp-includes/sodium_compat/src/Crypto.php:387": [
            "wp-includes/sodium_compat/src/Crypto.php",
            387
        ],
        "wp-includes/sodium_compat/src/Crypto32.php:387": [
            "wp-includes/sodium_compat/src/Crypto32.php",
            387
        ],
        "wp-includes/wp-db.php:2096": [
            "wp-includes/wp-db.php",
            2096
        ]
    },
    ":class": "ShrinkPress\\Build\\Entity\\Funcs\\WordPress_Func"
}