{
    "callbacks": [],
    "functionName": "populate_roles_280",
    "filename": "wp-admin/includes/schema.php",
    "docCommentLine": 894,
    "startLine": 899,
    "endLine": 905,
    "calls": {
        "wp-admin/includes/schema.php:696": [
            "wp-admin/includes/schema.php",
            696
        ],
        "wp-admin/includes/upgrade.php:1611": [
            "wp-admin/includes/upgrade.php",
            1611
        ]
    },
    ":class": "ShrinkPress\\Index\\Entity\\Funcs\\WordPress_Func"
}