{
    "callbacks": [],
    "functionName": "wp_checkdate",
    "filename": "wp-includes/functions.php",
    "docCommentLine": 6392,
    "startLine": 6405,
    "endLine": 6415,
    "calls": {
        "wp-admin/includes/post.php:181": [
            "wp-admin/includes/post.php",
            181
        ],
        "wp-includes/canonical.php:144": [
            "wp-includes/canonical.php",
            144
        ],
        "wp-includes/class-wp-customize-manager.php:2469": [
            "wp-includes/class-wp-customize-manager.php",
            2469
        ],
        "wp-includes/class-wp-date-query.php:427": [
            "wp-includes/class-wp-date-query.php",
            427
        ],
        "wp-includes/class-wp-date-query.php:443": [
            "wp-includes/class-wp-date-query.php",
            443
        ],
        "wp-includes/class-wp-query.php:846": [
            "wp-includes/class-wp-query.php",
            846
        ],
        "wp-includes/ms-site.php:617": [
            "wp-includes/ms-site.php",
            617
        ],
        "wp-includes/post.php:3733": [
            "wp-includes/post.php",
            3733
        ]
    },
    ":class": "ShrinkPress\\Build\\Entity\\Funcs\\WordPress_Func"
}