{
    "callbacks": [],
    "functionName": "wp_clear_scheduled_hook",
    "filename": "wp-includes/cron.php",
    "docCommentLine": 382,
    "startLine": 400,
    "endLine": 450,
    "calls": {
        "wp-admin/includes/upgrade.php:1869": [
            "wp-admin/includes/upgrade.php",
            1869
        ],
        "wp-admin/includes/upgrade.php:1885": [
            "wp-admin/includes/upgrade.php",
            1885
        ],
        "wp-admin/includes/upgrade.php:2074": [
            "wp-admin/includes/upgrade.php",
            2074
        ],
        "wp-includes/post.php:3059": [
            "wp-includes/post.php",
            3059
        ],
        "wp-includes/post.php:4308": [
            "wp-includes/post.php",
            4308
        ],
        "wp-includes/post.php:6797": [
            "wp-includes/post.php",
            6797
        ],
        "wp-includes/post.php:6814": [
            "wp-includes/post.php",
            6814
        ]
    },
    ":class": "ShrinkPress\\Build\\Entity\\Funcs\\WordPress_Func"
}