{
    "callbacks": [],
    "functionName": "wp_check_php_version",
    "filename": "wp-admin/includes/misc.php",
    "docCommentLine": 1391,
    "startLine": 1399,
    "endLine": 1452,
    "calls": {
        "wp-admin/includes/class-wp-site-health.php:704": [
            "wp-admin/includes/class-wp-site-health.php",
            704
        ],
        "wp-admin/includes/dashboard.php:39": [
            "wp-admin/includes/dashboard.php",
            39
        ],
        "wp-admin/includes/dashboard.php:1723": [
            "wp-admin/includes/dashboard.php",
            1723
        ],
        "wp-admin/includes/dashboard.php:1767": [
            "wp-admin/includes/dashboard.php",
            1767
        ]
    },
    ":class": "ShrinkPress\\Reframe\\Entity\\Funcs\\WordPress_Func"
}