{
    "callbacks": [],
    "functionName": "wp_imagecreatetruecolor",
    "filename": "wp-includes/media.php",
    "docCommentLine": 3154,
    "startLine": 3165,
    "endLine": 3172,
    "calls": {
        "wp-admin/includes/image-edit.php:451": [
            "wp-admin/includes/image-edit.php",
            451
        ],
        "wp-admin/includes/image-edit.php:480": [
            "wp-admin/includes/image-edit.php",
            480
        ],
        "wp-includes/class-wp-image-editor-gd.php:188": [
            "wp-includes/class-wp-image-editor-gd.php",
            188
        ],
        "wp-includes/class-wp-image-editor-gd.php:319": [
            "wp-includes/class-wp-image-editor-gd.php",
            319
        ],
        "wp-includes/class-wp-image-editor-gd.php:380": [
            "wp-includes/class-wp-image-editor-gd.php",
            380
        ]
    },
    ":class": "ShrinkPress\\Index\\Entity\\Funcs\\WordPress_Func"
}