{
    "callbacks": [],
    "functionName": "wp_send_json_error",
    "filename": "wp-includes/functions.php",
    "docCommentLine": 4059,
    "startLine": 4074,
    "endLine": 4096,
    "calls": {
        "wp-admin/includes/ajax-actions.php:352": [
            "wp-admin/includes/ajax-actions.php",
            352
        ],
        "wp-admin/includes/ajax-actions.php:2176": [
            "wp-admin/includes/ajax-actions.php",
            2176
        ],
        "wp-admin/includes/ajax-actions.php:2426": [
            "wp-admin/includes/ajax-actions.php",
            2426
        ],
        "wp-admin/includes/ajax-actions.php:2430": [
            "wp-admin/includes/ajax-actions.php",
            2430
        ],
        "wp-admin/includes/ajax-actions.php:2466": [
            "wp-admin/includes/ajax-actions.php",
            2466
        ],
        "wp-admin/includes/ajax-actions.php:2693": [
            "wp-admin/includes/ajax-actions.php",
            2693
        ],
        "wp-admin/includes/ajax-actions.php:2698": [
            "wp-admin/includes/ajax-actions.php",
            2698
        ],
        "wp-admin/includes/ajax-actions.php:2711": [
            "wp-admin/includes/ajax-actions.php",
            2711
        ],
        "wp-admin/includes/ajax-actions.php:2727": [
            "wp-admin/includes/ajax-actions.php",
            2727
        ],
        "wp-admin/includes/ajax-actions.php:2732": [
            "wp-admin/includes/ajax-actions.php",
            2732
        ],
        "wp-admin/includes/ajax-actions.php:2773": [
            "wp-admin/includes/ajax-actions.php",
            2773
        ],
        "wp-admin/includes/ajax-actions.php:2873": [
            "wp-admin/includes/ajax-actions.php",
            2873
        ],
        "wp-admin/includes/ajax-actions.php:2878": [
            "wp-admin/includes/ajax-actions.php",
            2878
        ],
        "wp-admin/includes/ajax-actions.php:2883": [
            "wp-admin/includes/ajax-actions.php",
            2883
        ],
        "wp-admin/includes/ajax-actions.php:2887": [
            "wp-admin/includes/ajax-actions.php",
            2887
        ],
        "wp-admin/includes/ajax-actions.php:2891": [
            "wp-admin/includes/ajax-actions.php",
            2891
        ],
        "wp-admin/includes/ajax-actions.php:2896": [
            "wp-admin/includes/ajax-actions.php",
            2896
        ],
        "wp-admin/includes/ajax-actions.php:2909": [
            "wp-admin/includes/ajax-actions.php",
            2909
        ],
        "wp-admin/includes/ajax-actions.php:2982": [
            "wp-admin/includes/ajax-actions.php",
            2982
        ],
        "wp-admin/includes/ajax-actions.php:2987": [
            "wp-admin/includes/ajax-actions.php",
            2987
        ],
        "wp-admin/includes/ajax-actions.php:2993": [
            "wp-admin/includes/ajax-actions.php",
            2993
        ],
        "wp-admin/includes/ajax-actions.php:3000": [
            "wp-admin/includes/ajax-actions.php",
            3000
        ],
        "wp-admin/includes/ajax-actions.php:3068": [
            "wp-admin/includes/ajax-actions.php",
            3068
        ],
        "wp-admin/includes/ajax-actions.php:3073": [
            "wp-admin/includes/ajax-actions.php",
            3073
        ],
        "wp-admin/includes/ajax-actions.php:3077": [
            "wp-admin/includes/ajax-actions.php",
            3077
        ],
        "wp-admin/includes/ajax-actions.php:3085": [
            "wp-admin/includes/ajax-actions.php",
            3085
        ],
        "wp-admin/includes/ajax-actions.php:3091": [
            "wp-admin/includes/ajax-actions.php",
            3091
        ],
        "wp-admin/includes/ajax-actions.php:3113": [
            "wp-admin/includes/ajax-actions.php",
            3113
        ],
        "wp-admin/includes/ajax-actions.php:3126": [
            "wp-admin/includes/ajax-actions.php",
            3126
        ],
        "wp-admin/includes/ajax-actions.php:3131": [
            "wp-admin/includes/ajax-actions.php",
            3131
        ],
        "wp-admin/includes/ajax-actions.php:3135": [
            "wp-admin/includes/ajax-actions.php",
            3135
        ],
        "wp-admin/includes/ajax-actions.php:3143": [
            "wp-admin/includes/ajax-actions.php",
            3143
        ],
        "wp-admin/includes/ajax-actions.php:3190": [
            "wp-admin/includes/ajax-actions.php",
            3190
        ],
        "wp-admin/includes/ajax-actions.php:3194": [
            "wp-admin/includes/ajax-actions.php",
            3194
        ],
        "wp-admin/includes/ajax-actions.php:3268": [
            "wp-admin/includes/ajax-actions.php",
            3268
        ],
        "wp-admin/includes/ajax-actions.php:3277": [
            "wp-admin/includes/ajax-actions.php",
            3277
        ],
        "wp-admin/includes/ajax-actions.php:3327": [
            "wp-admin/includes/ajax-actions.php",
            3327
        ],
        "wp-admin/includes/ajax-actions.php:3415": [
            "wp-admin/includes/ajax-actions.php",
            3415
        ],
        "wp-admin/includes/ajax-actions.php:3419": [
            "wp-admin/includes/ajax-actions.php",
            3419
        ],
        "wp-admin/includes/ajax-actions.php:3425": [
            "wp-admin/includes/ajax-actions.php",
            3425
        ],
        "wp-admin/includes/ajax-actions.php:3458": [
            "wp-admin/includes/ajax-actions.php",
            3458
        ],
        "wp-admin/includes/ajax-actions.php:3484": [
            "wp-admin/includes/ajax-actions.php",
            3484
        ],
        "wp-admin/includes/ajax-actions.php:3515": [
            "wp-admin/includes/ajax-actions.php",
            3515
        ],
        "wp-admin/includes/ajax-actions.php:3595": [
            "wp-admin/includes/ajax-actions.php",
            3595
        ],
        "wp-admin/includes/ajax-actions.php:3604": [
            "wp-admin/includes/ajax-actions.php",
            3604
        ],
        "wp-admin/includes/ajax-actions.php:3608": [
            "wp-admin/includes/ajax-actions.php",
            3608
        ],
        "wp-admin/includes/ajax-actions.php:3661": [
            "wp-admin/includes/ajax-actions.php",
            3661
        ],
        "wp-admin/includes/ajax-actions.php:3696": [
            "wp-admin/includes/ajax-actions.php",
            3696
        ],
        "wp-admin/includes/ajax-actions.php:3733": [
            "wp-admin/includes/ajax-actions.php",
            3733
        ],
        "wp-admin/includes/ajax-actions.php:3745": [
            "wp-admin/includes/ajax-actions.php",
            3745
        ],
        "wp-admin/includes/ajax-actions.php:3754": [
            "wp-admin/includes/ajax-actions.php",
            3754
        ],
        "wp-admin/includes/ajax-actions.php:3810": [
            "wp-admin/includes/ajax-actions.php",
            3810
        ],
        "wp-admin/includes/ajax-actions.php:3842": [
            "wp-admin/includes/ajax-actions.php",
            3842
        ],
        "wp-admin/includes/ajax-actions.php:3850": [
            "wp-admin/includes/ajax-actions.php",
            3850
        ],
        "wp-admin/includes/ajax-actions.php:3959": [
            "wp-admin/includes/ajax-actions.php",
            3959
        ],
        "wp-admin/includes/ajax-actions.php:3967": [
            "wp-admin/includes/ajax-actions.php",
            3967
        ],
        "wp-admin/includes/ajax-actions.php:3986": [
            "wp-admin/includes/ajax-actions.php",
            3986
        ],
        "wp-admin/includes/ajax-actions.php:4004": [
            "wp-admin/includes/ajax-actions.php",
            4004
        ],
        "wp-admin/includes/ajax-actions.php:4020": [
            "wp-admin/includes/ajax-actions.php",
            4020
        ],
        "wp-admin/includes/ajax-actions.php:4034": [
            "wp-admin/includes/ajax-actions.php",
            4034
        ],
        "wp-admin/includes/ajax-actions.php:4038": [
            "wp-admin/includes/ajax-actions.php",
            4038
        ],
        "wp-admin/includes/ajax-actions.php:4041": [
            "wp-admin/includes/ajax-actions.php",
            4041
        ],
        "wp-admin/includes/ajax-actions.php:4053": [
            "wp-admin/includes/ajax-actions.php",
            4053
        ],
        "wp-admin/includes/ajax-actions.php:4109": [
            "wp-admin/includes/ajax-actions.php",
            4109
        ],
        "wp-admin/includes/ajax-actions.php:4128": [
            "wp-admin/includes/ajax-actions.php",
            4128
        ],
        "wp-admin/includes/ajax-actions.php:4154": [
            "wp-admin/includes/ajax-actions.php",
            4154
        ],
        "wp-admin/includes/ajax-actions.php:4157": [
            "wp-admin/includes/ajax-actions.php",
            4157
        ],
        "wp-admin/includes/ajax-actions.php:4163": [
            "wp-admin/includes/ajax-actions.php",
            4163
        ],
        "wp-admin/includes/ajax-actions.php:4183": [
            "wp-admin/includes/ajax-actions.php",
            4183
        ],
        "wp-admin/includes/ajax-actions.php:4188": [
            "wp-admin/includes/ajax-actions.php",
            4188
        ],
        "wp-admin/includes/ajax-actions.php:4204": [
            "wp-admin/includes/ajax-actions.php",
            4204
        ],
        "wp-admin/includes/ajax-actions.php:4221": [
            "wp-admin/includes/ajax-actions.php",
            4221
        ],
        "wp-admin/includes/ajax-actions.php:4226": [
            "wp-admin/includes/ajax-actions.php",
            4226
        ],
        "wp-admin/includes/ajax-actions.php:4247": [
            "wp-admin/includes/ajax-actions.php",
            4247
        ],
        "wp-admin/includes/ajax-actions.php:4256": [
            "wp-admin/includes/ajax-actions.php",
            4256
        ],
        "wp-admin/includes/ajax-actions.php:4259": [
            "wp-admin/includes/ajax-actions.php",
            4259
        ],
        "wp-admin/includes/ajax-actions.php:4278": [
            "wp-admin/includes/ajax-actions.php",
            4278
        ],
        "wp-admin/includes/ajax-actions.php:4294": [
            "wp-admin/includes/ajax-actions.php",
            4294
        ],
        "wp-admin/includes/ajax-actions.php:4312": [
            "wp-admin/includes/ajax-actions.php",
            4312
        ],
        "wp-admin/includes/ajax-actions.php:4328": [
            "wp-admin/includes/ajax-actions.php",
            4328
        ],
        "wp-admin/includes/ajax-actions.php:4332": [
            "wp-admin/includes/ajax-actions.php",
            4332
        ],
        "wp-admin/includes/ajax-actions.php:4335": [
            "wp-admin/includes/ajax-actions.php",
            4335
        ],
        "wp-admin/includes/ajax-actions.php:4347": [
            "wp-admin/includes/ajax-actions.php",
            4347
        ],
        "wp-admin/includes/ajax-actions.php:4387": [
            "wp-admin/includes/ajax-actions.php",
            4387
        ],
        "wp-admin/includes/ajax-actions.php:4407": [
            "wp-admin/includes/ajax-actions.php",
            4407
        ],
        "wp-admin/includes/ajax-actions.php:4434": [
            "wp-admin/includes/ajax-actions.php",
            4434
        ],
        "wp-admin/includes/ajax-actions.php:4437": [
            "wp-admin/includes/ajax-actions.php",
            4437
        ],
        "wp-admin/includes/ajax-actions.php:4451": [
            "wp-admin/includes/ajax-actions.php",
            4451
        ],
        "wp-admin/includes/ajax-actions.php:4473": [
            "wp-admin/includes/ajax-actions.php",
            4473
        ],
        "wp-admin/includes/ajax-actions.php:4478": [
            "wp-admin/includes/ajax-actions.php",
            4478
        ],
        "wp-admin/includes/ajax-actions.php:4494": [
            "wp-admin/includes/ajax-actions.php",
            4494
        ],
        "wp-admin/includes/ajax-actions.php:4512": [
            "wp-admin/includes/ajax-actions.php",
            4512
        ],
        "wp-admin/includes/ajax-actions.php:4521": [
            "wp-admin/includes/ajax-actions.php",
            4521
        ],
        "wp-admin/includes/ajax-actions.php:4542": [
            "wp-admin/includes/ajax-actions.php",
            4542
        ],
        "wp-admin/includes/ajax-actions.php:4549": [
            "wp-admin/includes/ajax-actions.php",
            4549
        ],
        "wp-admin/includes/ajax-actions.php:4552": [
            "wp-admin/includes/ajax-actions.php",
            4552
        ],
        "wp-admin/includes/ajax-actions.php:4585": [
            "wp-admin/includes/ajax-actions.php",
            4585
        ],
        "wp-admin/includes/ajax-actions.php:4637": [
            "wp-admin/includes/ajax-actions.php",
            4637
        ],
        "wp-admin/includes/ajax-actions.php:4672": [
            "wp-admin/includes/ajax-actions.php",
            4672
        ],
        "wp-admin/includes/ajax-actions.php:4698": [
            "wp-admin/includes/ajax-actions.php",
            4698
        ],
        "wp-admin/includes/ajax-actions.php:4704": [
            "wp-admin/includes/ajax-actions.php",
            4704
        ],
        "wp-admin/includes/ajax-actions.php:4708": [
            "wp-admin/includes/ajax-actions.php",
            4708
        ],
        "wp-admin/includes/ajax-actions.php:4717": [
            "wp-admin/includes/ajax-actions.php",
            4717
        ],
        "wp-admin/includes/ajax-actions.php:4722": [
            "wp-admin/includes/ajax-actions.php",
            4722
        ],
        "wp-admin/includes/ajax-actions.php:4726": [
            "wp-admin/includes/ajax-actions.php",
            4726
        ],
        "wp-admin/includes/ajax-actions.php:4732": [
            "wp-admin/includes/ajax-actions.php",
            4732
        ],
        "wp-admin/includes/ajax-actions.php:4761": [
            "wp-admin/includes/ajax-actions.php",
            4761
        ],
        "wp-admin/includes/ajax-actions.php:4767": [
            "wp-admin/includes/ajax-actions.php",
            4767
        ],
        "wp-admin/includes/ajax-actions.php:4771": [
            "wp-admin/includes/ajax-actions.php",
            4771
        ],
        "wp-admin/includes/ajax-actions.php:4775": [
            "wp-admin/includes/ajax-actions.php",
            4775
        ],
        "wp-admin/includes/ajax-actions.php:4783": [
            "wp-admin/includes/ajax-actions.php",
            4783
        ],
        "wp-admin/includes/ajax-actions.php:4790": [
            "wp-admin/includes/ajax-actions.php",
            4790
        ],
        "wp-admin/includes/ajax-actions.php:4799": [
            "wp-admin/includes/ajax-actions.php",
            4799
        ],
        "wp-admin/includes/ajax-actions.php:4806": [
            "wp-admin/includes/ajax-actions.php",
            4806
        ],
        "wp-admin/includes/ajax-actions.php:4816": [
            "wp-admin/includes/ajax-actions.php",
            4816
        ],
        "wp-admin/includes/ajax-actions.php:4820": [
            "wp-admin/includes/ajax-actions.php",
            4820
        ],
        "wp-admin/includes/ajax-actions.php:4827": [
            "wp-admin/includes/ajax-actions.php",
            4827
        ],
        "wp-admin/includes/ajax-actions.php:4834": [
            "wp-admin/includes/ajax-actions.php",
            4834
        ],
        "wp-admin/includes/ajax-actions.php:4841": [
            "wp-admin/includes/ajax-actions.php",
            4841
        ],
        "wp-admin/includes/ajax-actions.php:4874": [
            "wp-admin/includes/ajax-actions.php",
            4874
        ],
        "wp-admin/includes/ajax-actions.php:4888": [
            "wp-admin/includes/ajax-actions.php",
            4888
        ],
        "wp-admin/includes/ajax-actions.php:4894": [
            "wp-admin/includes/ajax-actions.php",
            4894
        ],
        "wp-admin/includes/ajax-actions.php:4899": [
            "wp-admin/includes/ajax-actions.php",
            4899
        ],
        "wp-admin/includes/ajax-actions.php:4908": [
            "wp-admin/includes/ajax-actions.php",
            4908
        ],
        "wp-admin/includes/ajax-actions.php:4914": [
            "wp-admin/includes/ajax-actions.php",
            4914
        ],
        "wp-admin/includes/ajax-actions.php:4918": [
            "wp-admin/includes/ajax-actions.php",
            4918
        ],
        "wp-admin/includes/ajax-actions.php:4924": [
            "wp-admin/includes/ajax-actions.php",
            4924
        ],
        "wp-admin/includes/ajax-actions.php:4955": [
            "wp-admin/includes/ajax-actions.php",
            4955
        ],
        "wp-admin/includes/ajax-actions.php:4959": [
            "wp-admin/includes/ajax-actions.php",
            4959
        ],
        "wp-admin/includes/ajax-actions.php:4963": [
            "wp-admin/includes/ajax-actions.php",
            4963
        ],
        "wp-admin/includes/ajax-actions.php:4972": [
            "wp-admin/includes/ajax-actions.php",
            4972
        ],
        "wp-admin/includes/ajax-actions.php:4977": [
            "wp-admin/includes/ajax-actions.php",
            4977
        ],
        "wp-admin/includes/ajax-actions.php:4983": [
            "wp-admin/includes/ajax-actions.php",
            4983
        ],
        "wp-admin/includes/ajax-actions.php:4993": [
            "wp-admin/includes/ajax-actions.php",
            4993
        ],
        "wp-admin/includes/ajax-actions.php:5006": [
            "wp-admin/includes/ajax-actions.php",
            5006
        ],
        "wp-admin/includes/ajax-actions.php:5010": [
            "wp-admin/includes/ajax-actions.php",
            5010
        ],
        "wp-admin/includes/ajax-actions.php:5021": [
            "wp-admin/includes/ajax-actions.php",
            5021
        ],
        "wp-admin/includes/ajax-actions.php:5032": [
            "wp-admin/includes/ajax-actions.php",
            5032
        ],
        "wp-admin/includes/ajax-actions.php:5043": [
            "wp-admin/includes/ajax-actions.php",
            5043
        ],
        "wp-admin/includes/ajax-actions.php:5054": [
            "wp-admin/includes/ajax-actions.php",
            5054
        ],
        "wp-admin/includes/ajax-actions.php:5065": [
            "wp-admin/includes/ajax-actions.php",
            5065
        ],
        "wp-admin/includes/ajax-actions.php:5103": [
            "wp-admin/includes/ajax-actions.php",
            5103
        ],
        "wp-admin/includes/ajax-actions.php:5118": [
            "wp-admin/includes/ajax-actions.php",
            5118
        ],
        "wp-admin/includes/ajax-actions.php:5138": [
            "wp-admin/includes/ajax-actions.php",
            5138
        ],
        "wp-admin/includes/ajax-actions.php:5158": [
            "wp-admin/includes/ajax-actions.php",
            5158
        ],
        "wp-admin/includes/ajax-actions.php:5179": [
            "wp-admin/includes/ajax-actions.php",
            5179
        ],
        "wp-admin/includes/ajax-actions.php:5199": [
            "wp-admin/includes/ajax-actions.php",
            5199
        ],
        "wp-admin/includes/ajax-actions.php:5216": [
            "wp-admin/includes/ajax-actions.php",
            5216
        ],
        "wp-admin/includes/ajax-actions.php:5254": [
            "wp-admin/includes/ajax-actions.php",
            5254
        ],
        "wp-admin/includes/class-custom-background.php:544": [
            "wp-admin/includes/class-custom-background.php",
            544
        ],
        "wp-admin/includes/class-custom-background.php:549": [
            "wp-admin/includes/class-custom-background.php",
            549
        ],
        "wp-admin/includes/class-custom-image-header.php:1288": [
            "wp-admin/includes/class-custom-image-header.php",
            1288
        ],
        "wp-admin/includes/class-custom-image-header.php:1292": [
            "wp-admin/includes/class-custom-image-header.php",
            1292
        ],
        "wp-admin/includes/class-custom-image-header.php:1317": [
            "wp-admin/includes/class-custom-image-header.php",
            1317
        ],
        "wp-admin/includes/class-custom-image-header.php:1357": [
            "wp-admin/includes/class-custom-image-header.php",
            1357
        ],
        "wp-admin/includes/class-custom-image-header.php:1362": [
            "wp-admin/includes/class-custom-image-header.php",
            1362
        ],
        "wp-admin/includes/class-custom-image-header.php:1385": [
            "wp-admin/includes/class-custom-image-header.php",
            1385
        ],
        "wp-admin/includes/class-custom-image-header.php:1390": [
            "wp-admin/includes/class-custom-image-header.php",
            1390
        ],
        "wp-admin/includes/privacy-tools.php:300": [
            "wp-admin/includes/privacy-tools.php",
            300
        ],
        "wp-admin/includes/privacy-tools.php:307": [
            "wp-admin/includes/privacy-tools.php",
            307
        ],
        "wp-admin/includes/privacy-tools.php:313": [
            "wp-admin/includes/privacy-tools.php",
            313
        ],
        "wp-admin/includes/privacy-tools.php:321": [
            "wp-admin/includes/privacy-tools.php",
            321
        ],
        "wp-admin/includes/privacy-tools.php:329": [
            "wp-admin/includes/privacy-tools.php",
            329
        ],
        "wp-admin/includes/privacy-tools.php:398": [
            "wp-admin/includes/privacy-tools.php",
            398
        ],
        "wp-admin/includes/privacy-tools.php:413": [
            "wp-admin/includes/privacy-tools.php",
            413
        ],
        "wp-admin/includes/privacy-tools.php:526": [
            "wp-admin/includes/privacy-tools.php",
            526
        ],
        "wp-admin/includes/privacy-tools.php:740": [
            "wp-admin/includes/privacy-tools.php",
            740
        ],
        "wp-admin/includes/privacy-tools.php:816": [
            "wp-admin/includes/privacy-tools.php",
            816
        ],
        "wp-admin/includes/privacy-tools.php:884": [
            "wp-admin/includes/privacy-tools.php",
            884
        ],
        "wp-includes/class-wp-customize-manager.php:2403": [
            "wp-includes/class-wp-customize-manager.php",
            2403
        ],
        "wp-includes/class-wp-customize-manager.php:2407": [
            "wp-includes/class-wp-customize-manager.php",
            2407
        ],
        "wp-includes/class-wp-customize-manager.php:2412": [
            "wp-includes/class-wp-customize-manager.php",
            2412
        ],
        "wp-includes/class-wp-customize-manager.php:2419": [
            "wp-includes/class-wp-customize-manager.php",
            2419
        ],
        "wp-includes/class-wp-customize-manager.php:2423": [
            "wp-includes/class-wp-customize-manager.php",
            2423
        ],
        "wp-includes/class-wp-customize-manager.php:2430": [
            "wp-includes/class-wp-customize-manager.php",
            2430
        ],
        "wp-includes/class-wp-customize-manager.php:2448": [
            "wp-includes/class-wp-customize-manager.php",
            2448
        ],
        "wp-includes/class-wp-customize-manager.php:2452": [
            "wp-includes/class-wp-customize-manager.php",
            2452
        ],
        "wp-includes/class-wp-customize-manager.php:2471": [
            "wp-includes/class-wp-customize-manager.php",
            2471
        ],
        "wp-includes/class-wp-customize-manager.php:2477": [
            "wp-includes/class-wp-customize-manager.php",
            2477
        ],
        "wp-includes/class-wp-customize-manager.php:2585": [
            "wp-includes/class-wp-customize-manager.php",
            2585
        ],
        "wp-includes/class-wp-customize-manager.php:3080": [
            "wp-includes/class-wp-customize-manager.php",
            3080
        ],
        "wp-includes/class-wp-customize-manager.php:3084": [
            "wp-includes/class-wp-customize-manager.php",
            3084
        ],
        "wp-includes/class-wp-customize-manager.php:3088": [
            "wp-includes/class-wp-customize-manager.php",
            3088
        ],
        "wp-includes/class-wp-customize-manager.php:3099": [
            "wp-includes/class-wp-customize-manager.php",
            3099
        ],
        "wp-includes/class-wp-customize-manager.php:3109": [
            "wp-includes/class-wp-customize-manager.php",
            3109
        ],
        "wp-includes/class-wp-customize-manager.php:3118": [
            "wp-includes/class-wp-customize-manager.php",
            3118
        ],
        "wp-includes/class-wp-customize-manager.php:3129": [
            "wp-includes/class-wp-customize-manager.php",
            3129
        ],
        "wp-includes/class-wp-customize-manager.php:3304": [
            "wp-includes/class-wp-customize-manager.php",
            3304
        ],
        "wp-includes/class-wp-customize-manager.php:3308": [
            "wp-includes/class-wp-customize-manager.php",
            3308
        ],
        "wp-includes/class-wp-customize-manager.php:3319": [
            "wp-includes/class-wp-customize-manager.php",
            3319
        ],
        "wp-includes/class-wp-customize-manager.php:3328": [
            "wp-includes/class-wp-customize-manager.php",
            3328
        ],
        "wp-includes/class-wp-customize-manager.php:3602": [
            "wp-includes/class-wp-customize-manager.php",
            3602
        ],
        "wp-includes/class-wp-customize-manager.php:3616": [
            "wp-includes/class-wp-customize-manager.php",
            3616
        ],
        "wp-includes/class-wp-customize-manager.php:3620": [
            "wp-includes/class-wp-customize-manager.php",
            3620
        ],
        "wp-includes/class-wp-customize-manager.php:3624": [
            "wp-includes/class-wp-customize-manager.php",
            3624
        ],
        "wp-includes/class-wp-customize-manager.php:3633": [
            "wp-includes/class-wp-customize-manager.php",
            3633
        ],
        "wp-includes/class-wp-customize-manager.php:3636": [
            "wp-includes/class-wp-customize-manager.php",
            3636
        ],
        "wp-includes/class-wp-customize-manager.php:3652": [
            "wp-includes/class-wp-customize-manager.php",
            3652
        ],
        "wp-includes/class-wp-customize-manager.php:3659": [
            "wp-includes/class-wp-customize-manager.php",
            3659
        ],
        "wp-includes/class-wp-customize-manager.php:3663": [
            "wp-includes/class-wp-customize-manager.php",
            3663
        ],
        "wp-includes/class-wp-customize-manager.php:3668": [
            "wp-includes/class-wp-customize-manager.php",
            3668
        ],
        "wp-includes/class-wp-customize-manager.php:3673": [
            "wp-includes/class-wp-customize-manager.php",
            3673
        ],
        "wp-includes/class-wp-customize-manager.php:5714": [
            "wp-includes/class-wp-customize-manager.php",
            5714
        ],
        "wp-includes/class-wp-customize-manager.php:5773": [
            "wp-includes/class-wp-customize-manager.php",
            5773
        ],
        "wp-includes/class-wp-customize-nav-menus.php:109": [
            "wp-includes/class-wp-customize-nav-menus.php",
            109
        ],
        "wp-includes/class-wp-customize-nav-menus.php:114": [
            "wp-includes/class-wp-customize-nav-menus.php",
            114
        ],
        "wp-includes/class-wp-customize-nav-menus.php:121": [
            "wp-includes/class-wp-customize-nav-menus.php",
            121
        ],
        "wp-includes/class-wp-customize-nav-menus.php:272": [
            "wp-includes/class-wp-customize-nav-menus.php",
            272
        ],
        "wp-includes/class-wp-customize-nav-menus.php:289": [
            "wp-includes/class-wp-customize-nav-menus.php",
            289
        ],
        "wp-includes/class-wp-customize-nav-menus.php:927": [
            "wp-includes/class-wp-customize-nav-menus.php",
            927
        ],
        "wp-includes/class-wp-customize-nav-menus.php:931": [
            "wp-includes/class-wp-customize-nav-menus.php",
            931
        ],
        "wp-includes/class-wp-customize-nav-menus.php:935": [
            "wp-includes/class-wp-customize-nav-menus.php",
            935
        ],
        "wp-includes/class-wp-customize-nav-menus.php:941": [
            "wp-includes/class-wp-customize-nav-menus.php",
            941
        ],
        "wp-includes/class-wp-customize-nav-menus.php:954": [
            "wp-includes/class-wp-customize-nav-menus.php",
            954
        ],
        "wp-includes/class-wp-customize-nav-menus.php:960": [
            "wp-includes/class-wp-customize-nav-menus.php",
            960
        ],
        "wp-includes/class-wp-customize-nav-menus.php:966": [
            "wp-includes/class-wp-customize-nav-menus.php",
            966
        ],
        "wp-includes/class-wp-customize-nav-menus.php:982": [
            "wp-includes/class-wp-customize-nav-menus.php",
            982
        ],
        "wp-includes/class-wp-customize-widgets.php:1537": [
            "wp-includes/class-wp-customize-widgets.php",
            1537
        ],
        "wp-includes/class-wp-customize-widgets.php:1561": [
            "wp-includes/class-wp-customize-widgets.php",
            1561
        ],
        "wp-includes/class-wp-customize-widgets.php:1566": [
            "wp-includes/class-wp-customize-widgets.php",
            1566
        ],
        "wp-includes/customize/class-wp-customize-selective-refresh.php:330": [
            "wp-includes/customize/class-wp-customize-selective-refresh.php",
            330
        ],
        "wp-includes/customize/class-wp-customize-selective-refresh.php:332": [
            "wp-includes/customize/class-wp-customize-selective-refresh.php",
            332
        ],
        "wp-includes/customize/class-wp-customize-selective-refresh.php:341": [
            "wp-includes/customize/class-wp-customize-selective-refresh.php",
            341
        ],
        "wp-includes/customize/class-wp-customize-selective-refresh.php:369": [
            "wp-includes/customize/class-wp-customize-selective-refresh.php",
            369
        ],
        "wp-includes/deprecated.php:3933": [
            "wp-includes/deprecated.php",
            3933
        ],
        "wp-includes/deprecated.php:3950": [
            "wp-includes/deprecated.php",
            3950
        ]
    },
    ":class": "ShrinkPress\\Reframe\\Entity\\Funcs\\WordPress_Func"
}