{
    "docPackage": "WordPress",
    "docSubPackage": "Administration",
    "classes": {
        "WP_Screen": 15
    },
    "functions": [],
    "globals": {
        "hook_suffix": 223,
        "current_screen": 409,
        "taxnow": 409,
        "typenow": 409,
        "screen_layout_columns": 953,
        "wp_meta_boxes": 1107,
        "mode": 1317
    },
    "includes": [],
    "filename": "wp-admin/includes/class-wp-screen.php",
    ":class": "ShrinkPress\\Reframe\\Entity\\Files\\WP_Admin"
}